playoff/__init__.py
playoff/playoff.py
Playoff-0.7.6.dist-info/METADATA
Playoff-0.7.6.dist-info/WHEEL
Playoff-0.7.6.dist-info/top_level.txt
Playoff-0.7.6.dist-info/RECORD
