Metadata-Version: 2.1
Name: Playoff
Version: 0.7.6
Summary: This is the official OAuth 2.0 Python client SDK for the Playoff API
Home-page: https://github.com/officina/playoff-python-sdk
Author: Officina
Author-email: support@playoffgamification.io
License: UNKNOWN
Download-URL: https://github.com/officina/playoff-python-sdk/archive/0.7.6.tar.gz
Keywords: REST,Playoff API,Playoff SDK,Gamification
Platform: UNKNOWN
Classifier: Development Status :: 3 - Alpha
Classifier: Intended Audience :: Developers
Classifier: Programming Language :: Python :: 3.6
